[
  {
    "invite": "https://discord.gg/QAFXFtZ",
    "tags": "commands minecraftcommands minecraft commands mcc /r/mcc /r/minecraftcommands"
  },
  {
    "invite": "https://discord.gg/QRE99eS",
    "tags": "maptesting map testing playtesting play testing playtest play test testing plagiatus"
  },
  {
    "invite": "https://discord.gg/Xqxbczm",
    "tags": "burp burps burpland vanillaburp"
  },
  {
    "invite": "https://discord.gg/fZQbxbg",
    "tags": "x11 blockbench modelling modeling models model jannis"
  },
  {
    "invite": "https://discord.gg/Tk9A6b7",
    "tags": "phi"
  }
]
